{
  "niche": "Attack Buffing",
  "description": "Operators that buff allies' attack",
  "lastUpdated": "2025-12-25",
  "operators": {
    "saria": "",
    "swire": "Buffs melee operators in surrounding tiles with bad uptime",
    "whislash": "For melee operators",
    "skadi_the_corrupting_heart": "",
    "aak": "Hard to tank the buff for operators but if tanked is very good",
    "pallas": "Usefulness of buff hindered by high SP costs",
    "heidi": "At the price of -3 block for operators who receive this buff",
    "bryophyta": "",
    "alanna": "",
    "mon3tr": "",
    "thorns_the_lodestar": ""
  },
  "relatedNiches": [
    "Attack Buffing"
  ]
}